jaxmg/__init__.py
jaxmg/_cyclic_1d.py
jaxmg/_potri.py
jaxmg/_potrs.py
jaxmg/_syevd.py
jaxmg/utils.py
jaxmg/cu12/libcyclic.so
jaxmg/cu12/libpotri.so
jaxmg/cu12/libpotrs.so
jaxmg/cu12/libpotrs_mp.so
jaxmg/cu12/libsyevd.so
jaxmg/cu12/libsyevd_no_V.so
jaxmg/cu13/libcyclic.so
jaxmg/cu13/libpotri.so
jaxmg/cu13/libpotrs.so
jaxmg/cu13/libpotrs_mp.so
jaxmg/cu13/libsyevd.so
jaxmg/cu13/libsyevd_no_V.so
jaxmg-0.0.3.dist-info/METADATA
jaxmg-0.0.3.dist-info/WHEEL
jaxmg-0.0.3.dist-info/top_level.txt
jaxmg-0.0.3.dist-info/RECORD
jaxmg-0.0.3.dist-info/licenses/LICENSE
