Metadata-Version: 2.4
Name: jaxmg
Version: 0.0.3
Summary: JAXMg provides a C++ interface between JAX and cuSolverMg, NVIDIA's multi-GPU linear solver. 
Author: Roeland Wiersema
License-Expression: Apache-2.0
Project-URL: Homepage, https://github.com/therooler/jaxmg
Project-URL: Issues, https://github.com/therooler/jaxmg/issues
Project-URL: Docs, https://therooler.github.io/jaxmg/
Classifier: Programming Language :: Python :: 3
Requires-Python: >=3.11
License-File: LICENSE
Requires-Dist: jax>=0.6.2; sys_platform == "linux"
Provides-Extra: docs
Requires-Dist: jax>=0.6.2; extra == "docs"
Requires-Dist: mkdocs==1.6.1; extra == "docs"
Requires-Dist: mkdocs-material==9.6.23; extra == "docs"
Requires-Dist: mkdocstrings==0.30.1; extra == "docs"
Requires-Dist: mkdocs-exclude==1.0.2; extra == "docs"
Requires-Dist: mkdocs-ipynb==0.1.1; extra == "docs"
Requires-Dist: hippogriffe==0.2.2; extra == "docs"
Provides-Extra: dev
Requires-Dist: matplotlib>=3.10.3; extra == "dev"
Requires-Dist: jax[cuda12]>=0.6.2; extra == "dev"
Requires-Dist: pytest==8.2.1; extra == "dev"
Requires-Dist: mkdocs==1.6.1; extra == "dev"
Requires-Dist: mkdocs-material==9.6.23; extra == "dev"
Requires-Dist: mkdocstrings==0.30.1; extra == "dev"
Requires-Dist: mkdocs-exclude==1.0.2; extra == "dev"
Requires-Dist: mkdocs-ipynb==0.1.1; extra == "dev"
Requires-Dist: hippogriffe==0.2.2; extra == "dev"
Provides-Extra: cuda12
Requires-Dist: jax[cuda12]>=0.7.2; extra == "cuda12"
Provides-Extra: cuda13
Requires-Dist: jax[cuda13]>=0.7.2; extra == "cuda13"
Provides-Extra: cuda12-local
Requires-Dist: jax[cuda12-local]>=0.6.2; extra == "cuda12-local"
Provides-Extra: cuda13-local
Requires-Dist: jax[cuda13-local]>=0.7.2; extra == "cuda13-local"
Dynamic: license-file
